mosaik_web/__init__.py
mosaik_web/mosaik.py
mosaik_web/server.py
mosaik_web/html/index.html
mosaik_web/html/media/d3.min.js
mosaik_web/html/media/main.css
mosaik_web/html/media/mosaik.js
mosaik_web/html/media/snord.json
mosaik.Web_SemVer-0.2.3rc20230502220306.dist-info/AUTHORS.txt
mosaik.Web_SemVer-0.2.3rc20230502220306.dist-info/LICENSE.txt
mosaik.Web_SemVer-0.2.3rc20230502220306.dist-info/METADATA
mosaik.Web_SemVer-0.2.3rc20230502220306.dist-info/WHEEL
mosaik.Web_SemVer-0.2.3rc20230502220306.dist-info/entry_points.txt
mosaik.Web_SemVer-0.2.3rc20230502220306.dist-info/top_level.txt
mosaik.Web_SemVer-0.2.3rc20230502220306.dist-info/RECORD
