Metadata-Version: 2.1
Name: mosaik.Web-SemVer
Version: 0.2.3rc20230502220306
Summary: A simple simulation visualization for the browser.
Home-page: https://bitbucket.org/mosaik/mosaik-web
Author: Stefan Scherfke
Author-email: mosaik@offis.de
Maintainer: Bengt Lüers
Maintainer-email: bengt.lueers@gmail.com
License: UNKNOWN
Platform: UNKNOWN
Classifier: Development Status :: 4 - Beta
Classifier: Environment :: Console
Classifier: Environment :: Web Environment
Classifier: Intended Audience :: Science/Research
Classifier: License :: OSI Approved :: GNU Lesser General Public License v2 (LGPLv2)
Classifier: Natural Language :: English
Classifier: Operating System :: OS Independent
Classifier: Programming Language :: Python
Classifier: Programming Language :: Python :: 3
Classifier: Programming Language :: Python :: 3.7
Classifier: Programming Language :: Python :: 3.8
Classifier: Programming Language :: Python :: 3.9
Classifier: Topic :: Scientific/Engineering
Requires-Dist: arrow (>=0.4.2)
Requires-Dist: networkx (>=2.0)
